setup.cfg
setup.py
pincode_map/__init__.py
pincode_map/pincodemap.py
pincode_map.egg-info/PKG-INFO
pincode_map.egg-info/SOURCES.txt
pincode_map.egg-info/dependency_links.txt
pincode_map.egg-info/not-zip-safe
pincode_map.egg-info/top_level.txt