Metadata-Version: 1.0
Name: pincode-map
Version: 1.0
Summary: Validate and Mapping Pincode to Locality, City and State 
Home-page: https://github.com/manti/pincode_map
Author: Manti HS
Author-email: manti.rvce@gmail.com
License: MIT
Platform: UNKNOWN
